LICENSE
README.md
setup.cfg
setup.py
pyctr/__init__.py
pyctr/common.py
pyctr/fileio.py
pyctr/util.py
pyctr/cmd/__init__.py
pyctr/cmd/__main__.py
pyctr/cmd/checkenv.py
pyctr/crypto/__init__.py
pyctr/crypto/engine.py
pyctr/crypto/seeddb.py
pyctr/type/__init__.py
pyctr/type/cci.py
pyctr/type/cdn.py
pyctr/type/cia.py
pyctr/type/exefs.py
pyctr/type/nand.py
pyctr/type/ncch.py
pyctr/type/romfs.py
pyctr/type/sd.py
pyctr/type/sdfs.py
pyctr/type/sdtitle.py
pyctr/type/smdh.py
pyctr/type/tmd.py
pyctr/type/base/__init__.py
pyctr/type/base/typereader.py
pyctr/type/config/__init__.py
pyctr/type/config/blocks.py
pyctr/type/config/save.py
pyctr/type/save/__init__.py
pyctr/type/save/cmac.py
pyctr/type/save/common.py
pyctr/type/save/diff.py
pyctr/type/save/disa.py
pyctr/type/save/partition.py
pyctr/type/save/partdesc/__init__.py
pyctr/type/save/partdesc/common.py
pyctr/type/save/partdesc/difi.py
pyctr/type/save/partdesc/dpfs.py
pyctr/type/save/partdesc/ivfc.py
pyctr_edc.egg-info/PKG-INFO
pyctr_edc.egg-info/SOURCES.txt
pyctr_edc.egg-info/dependency_links.txt
pyctr_edc.egg-info/entry_points.txt
pyctr_edc.egg-info/requires.txt
pyctr_edc.egg-info/top_level.txt