Metadata-Version: 2.1
Name: pyctr-edc
Version: 0.8.0.dev0
Summary: Python library to parse several Nintendo 3DS files
Home-page: https://github.com/edisonwong520/pyctr
Author: Edison wong
Author-email: edisonwong@gmail.com
License: MIT
Platform: UNKNOWN
Classifier: License :: OSI Approved :: MIT License
Classifier: Programming Language :: Python :: 3
Classifier: Programming Language :: Python :: 3.8
Classifier: Programming Language :: Python :: 3.9
Classifier: Programming Language :: Python :: 3.10
Classifier: Programming Language :: Python :: 3.11
Provides-Extra: images
License-File: LICENSE
